aicommunicate/__init__.py
aicommunicate/coral.py
aicommunicate/parse.py
aicommunicate/parser/__init__.py
aicommunicate/parser/_base.py
aicommunicate/parser/pbase64.py
aicommunicate/parser/pjson.py
aicommunicate/parser/pxml.py
aicommunicate/types/__init__.py
aicommunicate/types/config.py
aicommunicate/types/payload.py
aicommunicate/utils/__init__.py
aicommunicate/utils/constants.py
aicommunicate/utils/exception.py
aicommunicate/utils/metrics.py
aicommunicate/utils/sched.py
aicommunicate/utils/util.py
aicommunicate-0.1.0.dist-info/METADATA
aicommunicate-0.1.0.dist-info/WHEEL
aicommunicate-0.1.0.dist-info/RECORD
