Metadata-Version: 2.1
Name: aicommunicate
Version: 0.1.0
Summary: 
Author: CachCheng
Author-email: tkggpdc2007@163.com
Requires-Python: >=3.8,<4.0
Classifier: Programming Language :: Python :: 3
Classifier: Programming Language :: Python :: 3.8
Classifier: Programming Language :: Python :: 3.9
Classifier: Programming Language :: Python :: 3.10
Classifier: Programming Language :: Python :: 3.11
Classifier: Programming Language :: Python :: 3.12
Requires-Dist: apscheduler (>=3.10.4,<4.0.0)
Requires-Dist: loguru (>=0.7.2,<0.8.0)
Requires-Dist: opencv-python (>=4.8,<4.9)
Requires-Dist: paho-mqtt (>=2.1.0,<3.0.0)
Requires-Dist: pydantic (>=2.7.1,<3.0.0)
Requires-Dist: pyzmq (>=26.0.3,<27.0.0)
Requires-Dist: requests (>=2.31.0,<3.0.0)
Requires-Dist: sharedarray (>=3.2.3,<4.0.0)
Requires-Dist: wrapyfi (>=0.4.43,<0.5.0)
Requires-Dist: xmltodict (>=0.13.0,<0.14.0)
